{"heading":"The Lord has done great things for His people, Israel.","number":126,"verseCount":6,"verses":[[1,["When the ",[["Lord",["small-caps"]],["deity-name"]]," turned again the captivity of Zion, we were like them that dream."]],[2,["Then was our mouth filled with laughter, and our tongue with singing: then said they among the heathen, The ",[["Lord",["small-caps"]],["deity-name"]]," hath ",["done",["study-note-ref","a",[["Ezek. 36:36","ot/ezek/36.36"],"."]]]," great ",["things",["study-note-ref","b",[["Luke 1:49","nt/luke/1.49"],"."]]]," for them."]],[3,["The ",[["Lord",["small-caps"]],["deity-name"]]," hath done great things for us; ",["whereof",["clarity-word"]]," we are glad."]],[4,[["Turn again",["study-note-ref","a",["OR Restore us from."]]]," our captivity, O ",[["Lord",["small-caps"]],["deity-name"]],", as the streams in the south."]],[5,["They that sow in tears shall reap in ",["joy",["study-note-ref","a",[["TG Joy","tg/joy"],"."]]],"."]],[6,["He that goeth forth and weepeth, bearing precious ",["seed",["study-note-ref","a",[["D&C 75:5","dc-testament/dc/75.5"],"."]]],", shall doubtless come again with rejoicing, bringing his ",["sheaves",["study-note-ref","b",[["D&C 31:5","dc-testament/dc/31.5"],"; ",["33:9","dc-testament/dc/33.9"],"."]]]," ",["with him.",["clarity-word"]]]]],"volume":"ot"}