{"number":73,"verseCount":28,"verses":[[1,["Truly God ",["is",["clarity-word"]]," good to Israel, ",["even",["clarity-word"]]," to such as are of a ",["clean",["study-note-ref","a",[["TG Purity","tg/purity"],"."]]]," heart."]],[2,["But as for me, my feet were almost gone; my steps had well nigh slipped."]],[3,["For I was ",["envious",["study-note-ref","a",[["TG Envy","tg/envy"],"."]]]," at the foolish, ",["when",["clarity-word"]]," I saw the prosperity of the wicked."]],[4,["For ",["there are",["clarity-word"]]," no bands in their death: but their strength ",["is",["clarity-word"]]," firm."]],[5,["They ",["are",["clarity-word"]]," not in trouble ",["as other",["clarity-word"]]," men; neither are they plagued like ",["other",["clarity-word"]]," men."]],[6,["Therefore pride compasseth them about as a ",["chain",["study-note-ref","a",["OR necklace."]]],"; violence covereth them ",["as",["clarity-word"]]," a garment."]],[7,["Their eyes stand out with ",["fatness",["study-note-ref","a",[["D&C 68:31","dc-testament/dc/68.31"],"."]]],": they have more than heart could wish."]],[8,["They are corrupt, and speak wickedly ",["concerning",["clarity-word"]]," oppression: they ",["speak",["study-note-ref","a",[["2 Pet. 2:18 (10–19)","nt/2-pet/2.18"],"."]]]," loftily."]],[9,["They set their mouth against the heavens, and their tongue walketh through the earth."]],[10,["Therefore his people return hither: and waters of a full ",["cup",["clarity-word"]]," are wrung out to them."]],[11,["And they say, How doth God ",["know",["study-note-ref","a",[["Job 22:13","ot/job/22.13"],"."]]],"? and is there knowledge in the most High?"]],[12,["Behold, these ",["are",["clarity-word"]]," the ungodly, who ",["prosper",["study-note-ref","a",[["Job 12:6","ot/job/12.6"],"; ",["Ps. 17:14","ot/ps/17.14"],"; ",["Hel. 7:5 (4–6)","bofm/hel/7.5"],"."]]]," in the ",["world",["study-note-ref","b",[["TG Worldliness","tg/worldliness"],"."]]],"; they increase ",["in",["clarity-word"]]," riches."]],[13,["Verily I have cleansed my heart ",["in",["clarity-word"]]," vain, and ",["washed",["study-note-ref","a",[["TG Wash","tg/wash"],"."]]]," my hands in innocency."]],[14,["For all the day long have I been plagued, and chastened every morning."]],[15,["If I say, I will speak thus; behold, I should offend ",["against",["clarity-word"]]," the generation of thy children."]],[16,["When I thought to know this, it ",["was",["clarity-word"]]," too painful for me;"]],[17,["Until I went into the ",["sanctuary",["study-note-ref","a",[["2 Kgs. 19:1","ot/2-kgs/19.1"],"; ",["Ps. 20:2","ot/ps/20.2"],"."]]]," of God; ",["then",["clarity-word"]]," understood I their ",["end",["study-note-ref","b",[["2 Ne. 30:10","bofm/2-ne/30.10"],"; ",["D&C 29:17","dc-testament/dc/29.17"],"; ",["JS—M 1:55","pgp/js-m/1.55"],"."]]],"."]],[18,["Surely thou didst set them in slippery places: thou castedst them down into destruction."]],[19,["How are they ",["brought",["clarity-word"]]," into desolation, as in a moment! they are utterly consumed with terrors."]],[20,["As a dream when ",["one",["clarity-word"]]," awaketh; ",["so,",["clarity-word"]]," O Lord, when thou ",["awakest",["study-note-ref","a",[["Ps. 78:65 (65–66)","ot/ps/78.65"],"."]]],", thou shalt ",["despise",["study-note-ref","b",[["2 Ne. 9:42 (41–42)","bofm/2-ne/9.42"],"."]]]," their image."]],[21,["Thus my heart was grieved, and I was ",["pricked",["study-note-ref","a",[["TG Conscience","tg/conscience"],"."]]]," in my reins."]],[22,["So foolish ",["was",["clarity-word"]]," I, and ignorant: I was ",["as",["clarity-word"]]," a ",["beast",["study-note-ref","a",[["Eccl. 3:18","ot/eccl/3.18"],"."]]]," before thee."]],[23,["Nevertheless I ",["am",["clarity-word"]]," continually ",["",761],"with thee: thou hast holden ",["me",["clarity-word"]]," by my right hand."]],[24,["Thou shalt ",["guide",["study-note-ref","a",[["TG Conscience","tg/conscience"],"."]]]," me with thy ",["counsel",["study-note-ref","b",[["TG Counsel","tg/counsel"],"."]]],", and afterward receive me ",["to",["clarity-word"]]," ",["glory",["study-note-ref","c",[["TG Eternal Life","tg/eternal-life"],"."]]],"."]],[25,["Whom have I in heaven ",["but thee?",["clarity-word"]]," and ",["there is",["clarity-word"]]," none upon earth ",["that",["clarity-word"]]," I desire beside thee."]],[26,["My ",["flesh",["study-note-ref","a",[["TG Flesh and Blood","tg/flesh-and-blood"],"."]]]," and my heart ",["faileth",["study-note-ref","b",[["Ps. 40:12 (12–13)","ot/ps/40.12"],"."]]],": ",["but",["clarity-word"]]," God ",["is",["clarity-word"]]," the ",["strength",["study-note-ref","c",[["TG Strength","tg/strength"],"."]]]," of my heart, and my ",["portion",["study-note-ref","d",[["Ps. 16:5","ot/ps/16.5"],"."]]]," for ever."]],[27,["For, lo, they that are far from thee shall perish: thou hast destroyed all them that go a whoring from thee."]],[28,["But ",["it is",["clarity-word"]]," good for me to draw near to God: I have put my trust in the Lord ",[["God",["small-caps"]],["deity-name"]],", that I may declare all thy works."]]],"volume":"ot"}