{"number":87,"verseCount":7,"verses":[{"number":1,"scriptureText":"HIS foundation is in the holy mountains."},{"number":2,"scriptureText":"The LORD loveth the gates of Zion more than all the dwellings of Jacob."},{"number":3,"scriptureText":"Glorious things are spoken of thee, O city of God. Selah."},{"number":4,"scriptureText":"I will make mention of Rahab and Babylon to them that know me: behold Philistia, and Tyre, with Ethiopia; this man was born there."},{"number":5,"scriptureText":"And of Zion it shall be said, This and that man was born in her: and the highest himself shall establish her."},{"number":6,"scriptureText":"The LORD shall count, when he writeth up the people, that this man was born there. Selah."},{"number":7,"scriptureText":"As well the singers as the players on instruments shall be there: all my springs are in thee."}],"volume":"ot"}