{"heading":"Aaron and his sons are to be washed, anointed, and consecrated—Various sacrificial rites are to be performed—Atonement is to be made for the sins of the people—The Lord promises to dwell among them.","number":29,"verseCount":46,"verses":[[1,["And this ",["is",["clarity-word"]]," the thing that thou shalt do unto them to ",["hallow",["study-note-ref","a",["OR consecrate or set apart."]]]," them, to minister unto me in the ",["priest’s",["study-note-ref","b",[["Lev. 21:10 (10–15)","ot/lev/21.10"],"."]]]," office: Take one ",["young bullock",["study-note-ref","c",["OR young bull (also ",["vv. 3, 10–12, 14, 36","ot/ex/29.3,10-12,14,36"],"). ",["Lev. 8:2","ot/lev/8.2"],"; ",["2 Chr. 13:9","ot/2-chr/13.9"],"."]]],", and two rams without blemish,"]],[2,["And ",["unleavened",["study-note-ref","a",[["Lev. 2:4","ot/lev/2.4"],"."]]]," bread, and cakes unleavened ",["tempered",["study-note-ref","b",["HEB mingled."]]]," with oil, and wafers unleavened ",["anointed",["study-note-ref","c",["OR smeared."]]]," with oil: ",["of",["clarity-word"]]," wheaten flour shalt thou make them."]],[3,["And thou shalt put them into one basket, and bring them in the basket, with the bullock and the two rams."]],[4,["And Aaron and his sons thou shalt bring unto the ",["door",["study-note-ref","a",["HEB opening of the tent of meeting (also ",["vv. 10–11, 30, 32, 42, 44","ot/ex/29.10-11,30,32,42,44"],")."]]]," of the tabernacle of the congregation, and shalt ",["wash",["study-note-ref","b",[["Lev. 8:6","ot/lev/8.6"],"; ",["D&C 124:39","dc-testament/dc/124.39"],"."]]]," them with water."]],[5,["And thou shalt take the ",["garments",["study-note-ref","a",[["Ex. 28:2 (1–5)","ot/ex/28.2"],"."]]],", and put upon Aaron the ",["coat",["study-note-ref","b",["OR tunic. ",["Lev. 8:7","ot/lev/8.7"],"."]]],", and the robe of the ",["ephod",["study-note-ref","c",[["Ex. 35:9","ot/ex/35.9"],"."]]],", and the ephod, and the breastplate, and gird him with the ",["curious",["study-note-ref","d",["OR skillfully woven."]]]," girdle of the ephod:"]],[6,["And thou shalt put the ",["mitre",["study-note-ref","a",["HEB turban."]]]," upon his head, and put the holy crown upon the mitre."]],[7,["Then shalt thou take the ",["anointing oil",["study-note-ref","a",[["Ex. 40:15 (12–15)","ot/ex/40.15"],"; ",["D&C 124:39","dc-testament/dc/124.39"],"."]]],", and pour ",["it",["clarity-word"]]," upon his head, and anoint him."]],[8,["And thou shalt bring his sons, and put coats upon them."]],[9,["And thou shalt ",["gird",["study-note-ref","a",[["Lev. 8:13","ot/lev/8.13"],"."]]]," them with girdles, Aaron and his sons, and ",["put the bonnets",["study-note-ref","b",["HEB bind headdresses."]]]," on them: and the ",["priest’s",["study-note-ref","c",[["TG Priest, Aaronic Priesthood","tg/priest-aaronic-priesthood"],"; ",["Priesthood, Aaronic","tg/priesthood-aaronic"],". ",["BD Priests","bd/priests"],"."]]]," office shall be theirs for a perpetual ",["statute",["study-note-ref","d",[["Ex. 27:21","ot/ex/27.21"],"."]]],": and thou shalt ",["consecrate",["study-note-ref","e",[["TG Priesthood, Authority","tg/priesthood-authority"],"."]]]," Aaron and his sons."]],[10,["And thou shalt cause a ",["bullock",["study-note-ref","a",[["Ezek. 43:19","ot/ezek/43.19"],"."]]]," to be brought before the tabernacle of the congregation: and Aaron and his sons shall put their ",["hands",["study-note-ref","b",[["TG Hands, Laying on of","tg/hands-laying-on-of"],"."]]]," upon the head of the bullock."]],[11,["And thou shalt kill the bullock before the ",[["Lord",["small-caps"]],["deity-name"]],", ",["by",["clarity-word"]]," the door of the tabernacle of the congregation."]],[12,["And thou shalt take of the blood of the bullock, and put ",["it",["clarity-word"]]," upon the horns of the altar with thy ",["",125],"finger, and ",["pour",["study-note-ref","a",[["Lev. 4:7","ot/lev/4.7"],"."]]]," all the blood beside the bottom of the ",["altar",["study-note-ref","b",[["Lev. 8:15 (1–17)","ot/lev/8.15"],"."]]],"."]],[13,["And thou shalt take all the fat that covereth the inwards, and the ",["caul",["study-note-ref","a",["HEB lobe."]]]," ",["that is",["clarity-word"]]," above the liver, and the two kidneys, and the fat that ",["is",["clarity-word"]]," upon them, and burn ",["them",["clarity-word"]]," upon the altar."]],[14,["But the flesh of the ",["bullock",["study-note-ref","a",[["Lev. 4:11 (3–12)","ot/lev/4.11"],"."]]],", and his skin, and his dung, shalt thou ",["burn",["study-note-ref","b",[["Ezek. 43:21","ot/ezek/43.21"],"."]]]," with fire without the camp: it ",["is",["clarity-word"]]," a sin offering."]],[15,[["¶ ",["para-mark"]],"Thou shalt also take one ram; and Aaron and his sons shall put their hands upon the head of the ram."]],[16,["And thou shalt slay the ram, and thou shalt take his blood, and sprinkle ",["it",["clarity-word"]]," round about upon the altar."]],[17,["And thou shalt cut the ram in pieces, and wash the inwards of him, and his legs, and put ",["them",["clarity-word"]]," ",["unto",["study-note-ref","a",["OR by."]]]," his pieces, and unto his head."]],[18,["And thou shalt burn the whole ram upon the altar: it ",["is",["clarity-word"]]," a burnt ",["offering",["study-note-ref","a",[["TG Sacrifice","tg/sacrifice"],"."]]]," unto the ",[["Lord",["small-caps"]],["deity-name"]],": it ",["is",["clarity-word"]]," a ",["sweet",["study-note-ref","b",["OR pleasing fragrance."]]]," ",["savour",["study-note-ref","c",[["Gen. 8:21","ot/gen/8.21"],"."]]],", an offering made by fire unto the ",[["Lord",["small-caps"]],["deity-name"]],"."]],[19,[["¶ ",["para-mark"]],"And thou shalt take the other ",["ram",["study-note-ref","a",[["Lev. 8:22","ot/lev/8.22"],"."]]],"; and Aaron and his sons shall put their hands upon the head of the ram."]],[20,["Then shalt thou kill the ram, and take of his blood, and put ",["it",["clarity-word"]]," upon the tip of the right ear of Aaron, and upon the tip of the right ear of his sons, and upon the thumb of their right hand, and upon the great toe of their right foot, and sprinkle the blood upon the altar round about."]],[21,["And thou shalt take of the blood that ",["is",["clarity-word"]]," upon the altar, and of the anointing oil, and sprinkle ",["it",["clarity-word"]]," upon Aaron, and upon his garments, and upon his sons, and upon the garments of his sons with him: and ",["he shall be hallowed",["study-note-ref","a",["OR thus he shall be sanctified."]]],", and his garments, and his sons, and his sons’ garments with him."]],[22,["Also thou shalt take of the ram the fat and the ",["rump",["study-note-ref","a",["HEB fat tail."]]],", and the fat that covereth the inwards, and the caul ",["above",["clarity-word"]]," the liver, and the two kidneys, and the fat that ",["is",["clarity-word"]]," upon them, and the right ",["shoulder",["study-note-ref","b",[["1 Sam. 9:24 (21–24)","ot/1-sam/9.24"],"."]]],"; for it ",["is",["clarity-word"]]," a ram of consecration:"]],[23,["And one loaf of bread, and one cake of oiled bread, and one wafer out of the basket of the ",["unleavened",["study-note-ref","a",[["TG Bread, Unleavened","tg/bread-unleavened"],"."]]]," bread that ",["is",["clarity-word"]]," before the ",[["Lord",["small-caps"]],["deity-name"]],":"]],[24,["And thou shalt put all in the hands of Aaron, and in the hands of his sons; and shalt ",["wave",["study-note-ref","a",["OR lift them up as an offering."]]]," them ",["for",["clarity-word"]]," a wave offering before the ",[["Lord",["small-caps"]],["deity-name"]],"."]],[25,["And thou shalt receive them of their hands, and burn ",["them",["clarity-word"]]," upon the altar for a burnt offering, for a sweet savour before the ",[["Lord",["small-caps"]],["deity-name"]],": it ",["is",["clarity-word"]]," an offering made by fire unto the ",[["Lord",["small-caps"]],["deity-name"]],"."]],[26,["And thou shalt take the breast of the ram of Aaron’s consecration, and wave it ",["for",["clarity-word"]]," a ",["wave",["study-note-ref","a",[["Lev. 10:14","ot/lev/10.14"],"."]]]," offering before the ",[["Lord",["small-caps"]],["deity-name"]],": and it shall be thy part."]],[27,["And thou shalt sanctify the breast of the wave offering, and the shoulder of the ",["heave",["study-note-ref","a",[["Num. 18:11","ot/num/18.11"],"."]]]," offering, which is ",["waved",["study-note-ref","b",["OR lifted up."]]],", and which is ",["heaved",["study-note-ref","c",["OR elevated."]]]," up, of the ram of the consecration, ",["even",["clarity-word"]]," of ",["that",["clarity-word"]]," which ",["is",["clarity-word"]]," for Aaron, and of ",["that",["clarity-word"]]," which is for his sons:"]],[28,["And it shall be Aaron’s and his sons’ by a ",["statute",["study-note-ref","a",[["Ex. 27:21","ot/ex/27.21"],"."]]]," for ever from the children of Israel: for it ",["is",["clarity-word"]]," an heave offering: and it shall be an heave offering from the children of Israel of the sacrifice of their peace offerings, ",["even",["clarity-word"]]," their heave offering unto the ",[["Lord",["small-caps"]],["deity-name"]],"."]],[29,[["¶ ",["para-mark"]],"And the holy ",["garments",["study-note-ref","a",[["Ex. 28:2 (1–5)","ot/ex/28.2"],"."]]]," of Aaron shall be his sons’ after him, to be ",["anointed",["study-note-ref","b",[["Num. 18:8","ot/num/18.8"],"."]]]," therein, and to be consecrated in them."]],[30,[["And",["clarity-word"]]," that son that is priest in his stead shall put them on seven days, when he cometh into the tabernacle of the congregation to minister in the holy ",["place.",["clarity-word"]]]],[31,[["¶ ",["para-mark"]],"And thou shalt take the ram of the consecration, and ",["seethe his flesh",["study-note-ref","a",["OR cook its flesh. ",["Lev. 8:31 (31–32)","ot/lev/8.31"],"."]]]," in the holy place."]],[32,["And Aaron and his sons shall eat the flesh of the ram, and the bread that ",["is",["clarity-word"]]," in the basket, ",["by",["clarity-word"]]," the door of the tabernacle of the congregation."]],[33,["And they shall ",["eat",["study-note-ref","a",[["Lev. 10:14 (12–15)","ot/lev/10.14"],"; ",["24:9 (5–9)","ot/lev/24.9"],"; ",["Luke 6:4","nt/luke/6.4"],"."]]]," those things wherewith the atonement was made, to consecrate ",["and",["clarity-word"]]," to sanctify them: but a ",["stranger",["study-note-ref","b",["OR alien."]]]," shall not eat ",["thereof,",["clarity-word"]]," because they ",["are",["clarity-word"]]," holy."]],[34,["And if ought of the flesh of the consecrations, or of the bread, remain unto the morning, then thou shalt burn the remainder with fire: it shall not be eaten, because it ",["is",["clarity-word"]]," holy."]],[35,["And thus shalt thou do unto Aaron, and to his sons, according to all ",["things",["clarity-word"]]," which I have commanded thee: ",["seven",["study-note-ref","a",[["Lev. 8:33","ot/lev/8.33"],"; ",["Ezek. 43:25","ot/ezek/43.25"],"."]]]," days shalt thou ",["consecrate them",["study-note-ref","b",["OR engage in the ordinance of setting them apart."]]],"."]],[36,["And thou shalt offer every day a bullock ",["for",["clarity-word"]]," a sin offering for atonement: and thou shalt cleanse the altar, when thou hast made an atonement for it, and thou shalt anoint it, to sanctify it."]],[37,["Seven days thou shalt make an atonement for the altar, and sanctify it; and it shall be an altar most holy: whatsoever toucheth the altar shall be holy."]],[38,[["¶ ",["para-mark"]],"Now this ",["is that",["clarity-word"]]," which thou shalt ",["offer",["study-note-ref","a",[["Num. 28:3 (3–8)","ot/num/28.3"],"; ",["1 Chr. 16:40","ot/1-chr/16.40"],"; ",["Dan. 8:11","ot/dan/8.11"],"."]]]," upon the altar; two lambs ",["of the first year",["study-note-ref","b",["HEB a year old."]]]," ",["day",["study-note-ref","c",[["2 Chr. 8:13 (12–13)","ot/2-chr/8.13"],"; ",["Ezek. 46:13","ot/ezek/46.13"],"; ",["Mosiah 13:30","bofm/mosiah/13.30"],"."]]]," by day continually."]],[39,["The one lamb thou shalt ",["offer",["study-note-ref","a",[["2 Kgs. 3:20","ot/2-kgs/3.20"],"."]]]," in the morning; and the other lamb thou shalt offer at even:"]],[40,["And with the one lamb a tenth ",["deal",["study-note-ref","a",["OR measure."]]]," of flour mingled with the fourth part of an hin of beaten ",["oil",["study-note-ref","b",[["Ezek. 45:24","ot/ezek/45.24"],"."]]],"; and the fourth part of an hin of wine ",["for",["clarity-word"]]," a ",["drink",["study-note-ref","c",[["Ezek. 45:17","ot/ezek/45.17"],"."]]]," offering."]],[41,["And the other lamb thou shalt offer at ",["even",["study-note-ref","a",[["Ps. 141:2","ot/ps/141.2"],"."]]],", and shalt do thereto according to the ",["meat",["study-note-ref","b",["HEB cereal, meal, or flour."]]]," offering of the morning, and according to the drink offering thereof, for a sweet savour, an offering made by fire unto the ",[["Lord",["small-caps"]],["deity-name"]],"."]],[42,[["This shall be",["clarity-word"]]," a continual burnt ",["offering",["study-note-ref","a",[["Num. 28:6 (3–8)","ot/num/28.6"],"."]]]," throughout your generations ",["at",["clarity-word"]]," the door of the ",["tabernacle",["study-note-ref","b",[["Ex. 33:7","ot/ex/33.7"],"."]]]," of the congregation before the ",[["Lord",["small-caps"]],["deity-name"]],": where I will meet you, to ",["speak",["study-note-ref","c",[["Lev. 16:2","ot/lev/16.2"],"."]]]," there unto thee."]],[43,["And there I will ",["meet",["study-note-ref","a",[["Ex. 25:22","ot/ex/25.22"],"."]]]," with the children of Israel, and ",["the ",["tabernacle",["study-note-ref","b",[["TG Temple","tg/temple"],"."]]],["clarity-word"]]," shall be sanctified by my glory."]],[44,["And I will sanctify the tabernacle of the congregation, and the altar: I will sanctify also both Aaron and his sons, to minister to me in the priest’s office."]],[45,[["¶ ",["para-mark"]],"And ",["I",["study-note-ref","a",[["Ex. 6:7","ot/ex/6.7"],"."]]]," will ",["dwell",["study-note-ref","b",[["Hag. 2:5","ot/hag/2.5"],"."]]]," ",["among",["study-note-ref","c",[["TG God, Presence of","tg/god-presence-of"],"."]]]," the children of Israel, and will be their ",["God",["study-note-ref","d",[["Ezek. 34:24 (20–31)","ot/ezek/34.24"],"."]]],"."]],[46,["And they shall know that I ",["am",["clarity-word"]]," the ",[["Lord",["small-caps"]],["deity-name"]]," their God, that brought them forth out of the land of Egypt, that I may dwell among them: I ",["am",["clarity-word"]]," the ",[["Lord",["small-caps"]],["deity-name"]]," their God."]]],"volume":"ot"}