{"number":20,"verseCount":27,"verses":[[1,["And the ",[["Lord",["small-caps"]],["deity-name"]]," spake unto Moses, saying,"]],[2,["Again, thou shalt say to the children of Israel, Whosoever ",["he be",["clarity-word"]]," of the children of Israel, or of the strangers that sojourn in Israel, that giveth ",["any",["clarity-word"]]," of his seed unto ",["Molech",["study-note-ref","a",[["TG Superstitions","tg/superstitions"],"."]]],"; he shall surely be put to death: the people of the land shall stone him with stones."]],[3,["And I will set my face against that man, and will cut him off from among his people; because he hath given of his seed unto Molech, to ",["defile",["study-note-ref","a",[["TG Sacrilege","tg/sacrilege"],"."]]]," my sanctuary, and to ",["profane",["study-note-ref","b",[["TG Profanity","tg/profanity"],"."]]]," my holy name."]],[4,["And if the people of the land do any ways hide their eyes from the man, when he giveth of his seed unto Molech, and ",["kill",["study-note-ref","a",[["Deut. 17:5 (2–3, 5)","ot/deut/17.5"],"."]]]," him not:"]],[5,["Then I will set my ",["face",["study-note-ref","a",[["Jer. 21:10","ot/jer/21.10"],"; ",["44:11","ot/jer/44.11"],"."]]]," against that man, and against his family, and will cut him off, and all that go a whoring after him, to commit ",["whoredom",["study-note-ref","b",[["Jer. 3:9 (8–9)","ot/jer/3.9"],"; ",["Ezek. 23:37","ot/ezek/23.37"],"."]]]," with Molech, from among their people."]],[6,[["¶ ",["para-mark"]],"And the soul that turneth ",["after",["study-note-ref","a",["HEB to magic or necromancy."]]]," such as have ",["familiar",["study-note-ref","b",[["TG Spirits, Evil or Unclean","tg/spirits-evil-or-unclean"],"."]]]," ",["spirits",["study-note-ref","c",[["TG Sorcery","tg/sorcery"],"."]]],", and after ",["wizards",["study-note-ref","d",[["2 Ne. 18:19","bofm/2-ne/18.19"],"."]]],", to go a whoring after them, I will even set my face against that soul, and will ",["cut him off",["study-note-ref","e",[["TG Excommunication","tg/excommunication"],"."]]]," from among his people."]],[7,[["¶ ",["para-mark"]],["Sanctify",["study-note-ref","a",[["Lev. 21:8","ot/lev/21.8"],"; ",["22:32","ot/lev/22.32"],"; ",["D&C 88:74","dc-testament/dc/88.74"],"."]]]," yourselves therefore, and be ye ",["holy",["study-note-ref","b",["OR saints."]]],": for I ",["am",["clarity-word"]]," the ",[["Lord",["small-caps"]],["deity-name"]]," your God."]],[8,["And ye shall keep my statutes, and do them: I ",["am",["clarity-word"]]," the ",[[["Lord",["study-note-ref","a",[["Lev. 19:3","ot/lev/19.3"],"."]]],["small-caps"]],["deity-name"]]," which sanctify you."]],[9,[["¶ ",["para-mark"]],"For every one that ",["curseth",["study-note-ref","a",[["TG Curse","tg/curse"],"."]]]," his ",["father",["study-note-ref","b",[["TG Family, Children, Duties of","tg/family-children-duties-of"],"."]]]," or his mother shall be surely put to death: he hath cursed his father or his mother; his ",["blood",["study-note-ref","c",[["TG Accountability","tg/accountability"],"."]]]," ",["shall be",["clarity-word"]]," upon him."]],[10,[["¶ ",["para-mark"]],"And the man that committeth adultery with ",["another",["clarity-word"]]," man’s wife, ",["even he",["clarity-word"]]," that committeth adultery with his ",["neighbour’s",["study-note-ref","a",[["Ezek. 18:11","ot/ezek/18.11"],"."]]]," wife, the ",["adulterer",["study-note-ref","b",[["TG Adulterer","tg/adulterer"],"; ",["Sexual Immorality","tg/sexual-immorality"],"."]]]," and the ",["adulteress",["study-note-ref","c",[["John 8:5","nt/john/8.5"],"."]]]," shall surely be put to ",["death",["study-note-ref","d",[["TG Capital Punishment","tg/capital-punishment"],"."]]],"."]],[11,["And the man that lieth with his ",["father’s",["study-note-ref","a",[["Deut. 22:30","ot/deut/22.30"],"."]]]," wife hath uncovered his father’s ",["nakedness",["study-note-ref","b",[["Lev. 18:8 (7–8)","ot/lev/18.8"],"."]]],": both of them shall surely be put to death; their blood ",["shall be",["clarity-word"]]," upon them."]],[12,["And if a man lie with his daughter in law, both of them shall surely be put to death: they have ",["wrought confusion",["study-note-ref","a",["OR done lewdness."]]],"; their blood ",["shall be",["clarity-word"]]," upon them."]],[13,["If a man ",["also lie with mankind",["study-note-ref","a",["HEB lies with a male."]]],", as he lieth with a ",["woman",["study-note-ref","b",[["TG Woman","tg/woman"],"."]]],", both of them have committed an ",["abomination",["study-note-ref","c",[["TG Homosexual Behavior","tg/homosexual-behavior"],"."]]],": they shall surely be put to death; their blood ",["shall be",["clarity-word"]]," upon them."]],[14,["And if a man take a wife and her mother, it ",["is",["clarity-word"]]," ",["wickedness",["study-note-ref","a",["OR lewdness or an evil device."]]],": they shall be burnt with fire, both he and they; that there be no wickedness among you."]],[15,["And if a man lie with a ",["beast",["study-note-ref","a",[["Deut. 27:21","ot/deut/27.21"],"."]]],", he shall surely be put to death: and ye shall slay the beast."]],[16,["And if a woman approach unto any beast, and lie down thereto, thou shalt kill the woman, and the beast: they shall surely be put to death; their blood ",["shall be",["clarity-word"]]," upon them."]],[17,["And if a man shall take his sister, his father’s daughter, or his mother’s daughter, and see her ",["nakedness",["study-note-ref","a",[["Deut. 27:22","ot/deut/27.22"],"."]]],", and she see his nakedness; it ",["is",["clarity-word"]]," a ",["wicked thing",["study-note-ref","b",["OR disgrace (Aramaism)."]]],"; and they shall be ",["cut off",["study-note-ref","c",["IE publicly excommunicated."]]]," in the sight of their people: he hath uncovered his sister’s nakedness; he shall bear his iniquity."]],[18,["And if a man shall lie with a woman having her sickness, and shall uncover her nakedness; he hath discovered her fountain, and she hath uncovered the fountain of her blood: and both of them shall be cut off from among their people."]],[19,["And thou shalt not uncover the nakedness of thy mother’s sister, nor of thy father’s sister: for he uncovereth his near kin: they shall bear their iniquity."]],[20,["And if a man shall lie with his uncle’s wife, he hath uncovered his uncle’s nakedness: they shall bear their sin; they shall die childless."]],[21,["And if a man shall take his brother’s wife, it ",["is",["clarity-word"]]," ",["an unclean thing",["study-note-ref","a",["HEB impurity; i.e., repulsive. ",["Lev. 18:16","ot/lev/18.16"],"; ",["Matt. 14:4 (3–4)","nt/matt/14.4"],"."]]],": he hath uncovered his brother’s nakedness; they shall be childless."]],[22,[["¶ ",["para-mark"]],"Ye shall therefore keep all my statutes, and all my judgments, and do them: that the land, whither I bring you to dwell therein, ",["spue",["study-note-ref","a",[["1 Ne. 17:38 (37–38)","bofm/1-ne/17.38"],"."]]]," you not out."]],[23,["And ye shall not ",["walk",["study-note-ref","a",[["TG Walking in Darkness","tg/walking-in-darkness"],"."]]]," in the manners of the ",["nation",["study-note-ref","b",[["Deut. 7:1 (1–2)","ot/deut/7.1"],"."]]],", which I cast out before you: for they committed all these things, and therefore I abhorred them."]],[24,["But I have said unto you, Ye shall inherit their land, and I will give it unto you to possess it, a land that floweth with ",["milk",["study-note-ref","a",[["D&C 38:18","dc-testament/dc/38.18"],"."]]]," and honey: I ",["am",["clarity-word"]]," the ",[["Lord",["small-caps"]],["deity-name"]]," your God, which have ",["separated",["study-note-ref","b",[["1 Kgs. 8:53","ot/1-kgs/8.53"],"."]]]," you from ",["other",["clarity-word"]]," people."]],[25,["Ye shall therefore ",["put difference between",["study-note-ref","a",["HEB distinguish between."]]]," clean beasts and unclean, and between unclean fowls and clean: and ye shall not make your souls abominable by beast, or by fowl, or by any manner of living thing that creepeth on the ground, which I have ",["separated",["study-note-ref","b",["HEB distinguished for you as impure."]]]," from you as ",["unclean",["study-note-ref","c",[["Acts 10:15","nt/acts/10.15"],"."]]],"."]],[26,["And ye shall be ",["holy",["study-note-ref","a",[["TG Peculiar People","tg/peculiar-people"],"."]]]," unto me: for I the ",[["Lord",["small-caps"]],["deity-name"]]," ",["am",["clarity-word"]]," ",["holy",["study-note-ref","b",[["TG Holiness","tg/holiness"],"."]]],", and have ",["severed",["study-note-ref","c",["HEB distinguished you from the nations. ",["TG Separation","tg/separation"],"."]]]," you from ",["other",["clarity-word"]]," people, that ye should be ",["mine",["study-note-ref","d",[["3 Ne. 24:17","bofm/3-ne/24.17"],"."]]],"."]],[27,[["¶ ",["para-mark"]],"A man also or woman that hath a ",["familiar spirit",["study-note-ref","a",["This is in Hebrew ov, a skin bottle used as an instrument of necromancy. ",["TG Spirits, Evil or Unclean","tg/spirits-evil-or-unclean"],"."]]],", or that is a wizard, shall surely be put to death: they shall stone them with stones: their ",["blood",["study-note-ref","b",[["Jacob 1:19","bofm/jacob/1.19"],"."]]]," ",["shall be",["clarity-word"]]," upon them."]]],"volume":"ot"}